askp/__init__.py
askp/__main__.py
askp/agent_response.py
askp/api.py
askp/cache.py
askp/cli.py
askp/cost_tracking.py
askp/costs.py
askp/deep_research.py
askp/executor.py
askp/expand.py
askp/file_utils.py
askp/formatters.py
askp/models.py
askp/output_fix.py
askp/prompts.py
askp/tips.py
askp/utils.py
askp/visualizations.py
askp/codecheck/__init__.py
askp/deprecated/askr.py
askp-2.4.5.dist-info/licenses/LICENSE
askp-2.4.5.dist-info/METADATA
askp-2.4.5.dist-info/WHEEL
askp-2.4.5.dist-info/entry_points.txt
askp-2.4.5.dist-info/top_level.txt
askp-2.4.5.dist-info/RECORD
